{"gasha_items":[{"card_id":1013130,"is_new":false,"is_dokkan_fes":false,"is_play_skill":false},{"card_id":1008520,"is_new":false,"is_dokkan_fes":false,"is_play_skill":false},{"card_id":1007660,"is_new":false,"is_dokkan_fes":false,"is_play_skill":false},{"card_id":1008590,"is_new":false,"is_dokkan_fes":false,"is_play_skill":false},{"card_id":1004010,"is_new":false,"is_dokkan_fes":false,"is_play_skill":false},{"card_id":1007700,"is_new":false,"is_dokkan_fes":false,"is_play_skill":false},{"card_id":1006720,"is_new":false,"is_dokkan_fes":false,"is_play_skill":false}],"scouter_description":"The Scouter reads unidentified Power Levels!\nCheck the Pick-up Characters!"}